app/__init__.py
app/local.py
darn-0.1.0.dist-info/LICENSE
darn-0.1.0.dist-info/METADATA
darn-0.1.0.dist-info/WHEEL
darn-0.1.0.dist-info/top_level.txt
darn-0.1.0.dist-info/RECORD
